dnoticias_services/__init__.py
dnoticias_services/apps.py
dnoticias_services/base_service.py
dnoticias_services/authentication/__init__.py
dnoticias_services/authentication/keycloak.py
dnoticias_services/mail/__init__.py
dnoticias_services/mail/base.py
dnoticias_services/mail/campaign.py
dnoticias_services/mail/mail.py
dnoticias_services/payments/__init__.py
dnoticias_services/payments/base.py
dnoticias_services/payments/choices.py
dnoticias_services/payments/coupons.py
dnoticias_services/payments/items.py
dnoticias_services/payments/orders.py
dnoticias_services/payments/payments.py
dnoticias_services/payments/providers.py
dnoticias_services/payments/subscriptions.py
dnoticias_services/subscriptions/__init__.py
dnoticias_services/subscriptions/address.py
dnoticias_services/subscriptions/base.py
dnoticias_services/subscriptions/billing.py
dnoticias_services/subscriptions/coupons.py
dnoticias_services/subscriptions/digital.py
dnoticias_services/subscriptions/subscription.py
dnoticias_services/subscriptions/user.py
dnoticias_services/utils/__init__.py
dnoticias_services/utils/request.py
django_dnoticias_services-1.0.7.31.dist-info/METADATA
django_dnoticias_services-1.0.7.31.dist-info/WHEEL
django_dnoticias_services-1.0.7.31.dist-info/top_level.txt
django_dnoticias_services-1.0.7.31.dist-info/RECORD
