Metadata-Version: 2.1
Name: django-dnoticias-services
Version: 1.0.7.31
Summary: UNKNOWN
Home-page: https://www.dnoticias.pt/
Author: Pedro Mendes
Author-email: pedro.trabalho.uma@gmail.com
Maintainer: Nelson Gonçalves
Maintainer-email: ngoncalves@dnoticias.pt
License: MIT
Platform: UNKNOWN
Requires-Dist: requests
Requires-Dist: django
Requires-Dist: python-keycloak
Requires-Dist: mozilla-django-oidc
